hands_rdf/RDF.py
hands_rdf/__init__.py
hands_rdf/features.py
hands_rdf/helpers.py
hands_rdf/Model/BaseModel.py
hands_rdf/Model/Config.py
hands_rdf/Model/MultiModels.py
hands_rdf/Model/__init__.py
hands_rdf-0.1.dist-info/LICENSE
hands_rdf-0.1.dist-info/METADATA
hands_rdf-0.1.dist-info/WHEEL
hands_rdf-0.1.dist-info/top_level.txt
hands_rdf-0.1.dist-info/RECORD
